[
  {
    "warehouseCode": "MAA-HUB",
    "city": "Chennai",
    "tier": 1,
    "hour": 12,
    "dayOfWeek": 4,
    "month": 10,
    "day": 14,
    "surgeMultiplier": 3.5,
    "inboundRatio": 0.921,
    "pendingRatio": 0.451,
    "staffRatio": 0.779,
    "utilization": 1.25,
    "congestionLevel": "CRITICAL"
  },
  {
    "warehouseCode": "DEL-HUB",
    "city": "Delhi",
    "tier": 1,
    "hour": 22,
    "dayOfWeek": 4,
    "month": 6,
    "day": 15,
    "surgeMultiplier": 1,
    "inboundRatio": 0.73,
    "pendingRatio": 0.201,
    "staffRatio": 0.702,
    "utilization": 0.718,
    "congestionLevel": "HIGH"
  },
  {
    "warehouseCode": "CCU-HUB",
    "city": "Kolkata",
    "tier": 1,
    "hour": 5,
    "dayOfWeek": 6,
    "month": 2,
    "day": 25,
    "surgeMultiplier": 1,
    "inboundRatio": 0.602,
    "pendingRatio": 0.066,
    "staffRatio": 0.391,
    "utilization": 0.639,
    "congestionLevel": "MEDIUM"
  },
  {
    "warehouseCode": "BLR-HUB",
    "city": "Bengaluru",
    "tier": 1,
    "hour": 1,
    "dayOfWeek": 0,
    "month": 4,
    "day": 17,
    "surgeMultiplier": 1,
    "inboundRatio": 0.786,
    "pendingRatio": 0.794,
    "staffRatio": 0.428,
    "utilization": 0.894,
    "congestionLevel": "CRITICAL"
  },
  {
    "warehouseCode": "BOM-HUB",
    "city": "Mumbai",
    "tier": 1,
    "hour": 11,
    "dayOfWeek": 5,
    "month": 6,
    "day": 27,
    "surgeMultiplier": 2,
    "inboundRatio": 0.351,
    "pendingRatio": 0.551,
    "staffRatio": 0.899,
    "utilization": 1.25,
    "congestionLevel": "CRITICAL"
  },
  {
    "warehouseCode": "CCU-HUB",
    "city": "Kolkata",
    "tier": 1,
    "hour": 16,
    "dayOfWeek": 0,
    "month": 2,
    "day": 26,
    "surgeMultiplier": 1,
    "inboundRatio": 0.111,
    "pendingRatio": 0.563,
    "staffRatio": 0.903,
    "utilization": 0.273,
    "congestionLevel": "LOW"
  },
  {
    "warehouseCode": "DEL-HUB",
    "city": "Delhi",
    "tier": 1,
    "hour": 1,
    "dayOfWeek": 6,
    "month": 8,
    "day": 26,
    "surgeMultiplier": 1,
    "inboundRatio": 0.703,
    "pendingRatio": 0.038,
    "staffRatio": 0.422,
    "utilization": 0.749,
    "congestionLevel": "HIGH"
  },
  {
    "warehouseCode": "BLR-HUB",
    "city": "Bengaluru",
    "tier": 1,
    "hour": 22,
    "dayOfWeek": 2,
    "month": 1,
    "day": 20,
    "surgeMultiplier": 2.8,
    "inboundRatio": 0.314,
    "pendingRatio": 0.404,
    "staffRatio": 0.553,
    "utilization": 1.107,
    "congestionLevel": "CRITICAL"
  },
  {
    "warehouseCode": "JAI-REG",
    "city": "Jaipur",
    "tier": 2,
    "hour": 8,
    "dayOfWeek": 5,
    "month": 8,
    "day": 8,
    "surgeMultiplier": 1,
    "inboundRatio": 0.165,
    "pendingRatio": 0.392,
    "staffRatio": 0.982,
    "utilization": 0.395,
    "congestionLevel": "LOW"
  },
  {
    "warehouseCode": "AMD-REG",
    "city": "Ahmedabad",
    "tier": 2,
    "hour": 4,
    "dayOfWeek": 0,
    "month": 1,
    "day": 5,
    "surgeMultiplier": 1,
    "inboundRatio": 0.111,
    "pendingRatio": 0.275,
    "staffRatio": 0.362,
    "utilization": 0.206,
    "congestionLevel": "LOW"
  },
  {
    "warehouseCode": "BOM-HUB",
    "city": "Mumbai",
    "tier": 1,
    "hour": 14,
    "dayOfWeek": 2,
    "month": 12,
    "day": 12,
    "surgeMultiplier": 1,
    "inboundRatio": 0.172,
    "pendingRatio": 0.446,
    "staffRatio": 0.919,
    "utilization": 0.453,
    "congestionLevel": "MEDIUM"
  },
  {
    "warehouseCode": "MAA-HUB",
    "city": "Chennai",
    "tier": 1,
    "hour": 9,
    "dayOfWeek": 4,
    "month": 9,
    "day": 28,
    "surgeMultiplier": 1,
    "inboundRatio": 0.267,
    "pendingRatio": 0.125,
    "staffRatio": 0.967,
    "utilization": 0.327,
    "congestionLevel": "LOW"
  },
  {
    "warehouseCode": "BLR-HUB",
    "city": "Bengaluru",
    "tier": 1,
    "hour": 6,
    "dayOfWeek": 2,
    "month": 2,
    "day": 3,
    "surgeMultiplier": 1,
    "inboundRatio": 0.646,
    "pendingRatio": 0.57,
    "staffRatio": 0.997,
    "utilization": 0.827,
    "congestionLevel": "HIGH"
  },
  {
    "warehouseCode": "JAI-REG",
    "city": "Jaipur",
    "tier": 2,
    "hour": 23,
    "dayOfWeek": 4,
    "month": 9,
    "day": 23,
    "surgeMultiplier": 1,
    "inboundRatio": 0.776,
    "pendingRatio": 0.193,
    "staffRatio": 0.735,
    "utilization": 0.837,
    "congestionLevel": "HIGH"
  },
  {
    "warehouseCode": "AMD-REG",
    "city": "Ahmedabad",
    "tier": 2,
    "hour": 15,
    "dayOfWeek": 5,
    "month": 7,
    "day": 19,
    "surgeMultiplier": 1,
    "inboundRatio": 0.678,
    "pendingRatio": 0.103,
    "staffRatio": 0.886,
    "utilization": 1.25,
    "congestionLevel": "CRITICAL"
  },
  {
    "warehouseCode": "AMD-REG",
    "city": "Ahmedabad",
    "tier": 2,
    "hour": 16,
    "dayOfWeek": 1,
    "month": 8,
    "day": 24,
    "surgeMultiplier": 1,
    "inboundRatio": 0.614,
    "pendingRatio": 0.566,
    "staffRatio": 0.935,
    "utilization": 1.25,
    "congestionLevel": "CRITICAL"
  },
  {
    "warehouseCode": "BLR-HUB",
    "city": "Bengaluru",
    "tier": 1,
    "hour": 14,
    "dayOfWeek": 3,
    "month": 2,
    "day": 13,
    "surgeMultiplier": 1.4,
    "inboundRatio": 0.338,
    "pendingRatio": 0.359,
    "staffRatio": 0.873,
    "utilization": 0.835,
    "congestionLevel": "HIGH"
  },
  {
    "warehouseCode": "LKO-REG",
    "city": "Lucknow",
    "tier": 2,
    "hour": 14,
    "dayOfWeek": 2,
    "month": 1,
    "day": 27,
    "surgeMultiplier": 2.2,
    "inboundRatio": 0.516,
    "pendingRatio": 0.25,
    "staffRatio": 0.76,
    "utilization": 1.25,
    "congestionLevel": "CRITICAL"
  },
  {
    "warehouseCode": "JAI-REG",
    "city": "Jaipur",
    "tier": 2,
    "hour": 10,
    "dayOfWeek": 5,
    "month": 3,
    "day": 12,
    "surgeMultiplier": 1,
    "inboundRatio": 0.532,
    "pendingRatio": 0.374,
    "staffRatio": 0.981,
    "utilization": 1.114,
    "congestionLevel": "CRITICAL"
  },
  {
    "warehouseCode": "HYD-REG",
    "city": "Hyderabad",
    "tier": 2,
    "hour": 5,
    "dayOfWeek": 5,
    "month": 9,
    "day": 13,
    "surgeMultiplier": 1,
    "inboundRatio": 0.693,
    "pendingRatio": 0.569,
    "staffRatio": 0.432,
    "utilization": 1.25,
    "congestionLevel": "CRITICAL"
  }
]